gempa_terkini/__init__.py
ltsearthquake_indonesia-0.3.1.dist-info/LICENSE
ltsearthquake_indonesia-0.3.1.dist-info/METADATA
ltsearthquake_indonesia-0.3.1.dist-info/WHEEL
ltsearthquake_indonesia-0.3.1.dist-info/top_level.txt
ltsearthquake_indonesia-0.3.1.dist-info/RECORD
