Metadata-Version: 2.1
Name: ltsearthquake-indonesia
Version: 0.3.1
Summary: This package will get the latest 
Home-page: https://github.com/pypa/sampleproject
Author: Rahman Aji Pratama 
Author-email: pratamaxadjie@gmail.com
License: UNKNOWN
Project-URL: Website , https://github.com/pypa/sampleproject/issues
Platform: UNKNOWN
Classifier: Programming Language :: Python :: 3
Classifier: License :: OSI Approved :: MIT License
Classifier: Operating System :: OS Independent
Classifier: Development Status :: 5 - Production/Stable
Requires-Python: >=3.6
License-File: LICENSE
